Workbook

Sheet USUAL
A2: FIXED INCOME
A3: INCOME | B3: AMOUNT | C3: RECEIVING DATE
A4: SALARY | B4: 26000 | C4: 5th date
A5: TA & DA | B5: 5000 | C5: 15nth date
A6: QATAR INCOME | B6: 12000 | C6: 30th date
A7: TOTAL | B7: =SUM(B4:B6) -> 43000
A9: LIABILITIES
A10: LOAN | B10: AMOUNT | C10: DUE DATE | D10: CLOSING DATE
A11: 10K LOAN | B11: 1000 | C11: 2nd date | D11: 46388
A12: 50K LOAN | B12: 2251 | C12: 2rd date | D12: 47300
A13: JBl EMI | B13: 1417 | C13: 2th date | D13: 46296
A14: 30K LOAN | B14: 1643 | C14: 5th date | D14: 46235
A15: OLA EMI | B15: 3883 | C15: 5th date | D15: 46388
A16: ACTIVA EMI | B16: 2699 | C16: 5th date
A17: AYALKOOTTAM LOAN | B17: 2500 | C17: 5th date
A18: CAR LOAN | B18: 11300 | C18: 7th date | D18: 46722
A19: HOUSE RENT | B19: 7500 | C19: 5-10th date
A20: CURRENT BILL | B20: 500
A21: MOBILE RECHARGE | B21: 700
A22: CREDIT CARD EMI | B22: 1247.6 | C22: 11-30th date | D22: 46204
A23: CREDIT CARD EMI | B23: 568.5 | C23: 11-30th date | D23: 46447
A24: CREDIT CARD EMI | B24: 350.47 | C24: 11-30th date | D24: 46508
A25: CREDIT CARD BILL | B25: =916 -> 916 | C25: 11-30th date | D25: 46905
A26: KURI | B26: 2000 | D26: 46357
A27: TOTAL | B27: =SUM(B11:B26) -> 40475.57
A29: CONTINGENT EXPENSES
A30: PERSONAL ENTERTAINMENT | B30: 1000
A31: PETROL | B31: 1500
A32: OTHER AVAILABLE | B32: =B7-42976 -> 24
A33: BALANCE | B33: =B7-(B27+B30+B31) -> 24.43
A36: DEBTS
A37: CREDIT CARD
A38: ACB COLLECTION
A39: OTHER PERSON

Sheet INCOME 
A1: 46143
A2: =IF(40500>C4," ഇനിയും "&(40500-C4)&" രൂപ കിട്ടാനുണ്ട്",IF(C4>40500,(C4-40500)&" രൂപ അധിക ചിലവ് . ","തുക tally ആയി")) -> 2445 രൂപ അധിക ചിലവ് .
A3: Date | B3: Details | C3: Cash In
C4: =SUM(C5:C9) -> 42945
A5: 46143 | B5: Qatar | C5: 12000
A6: 46147 | B6: Salary | C6: 24282
A7: 46157 | B7: TA& DA | C7: 4663
A8: 46158 | B8: BONUS | C8: 2000

Sheet LIABILITIES  OR EMI
B1: 46143
A2: Date | B2: Details | C2: Cash Out | D2: Warning
B3: ='INCOME '!C4-2500-C4 -> 4593
C4: =SUM(C5:C17) -> 35852
A5: 46143 | B5: Kuri | C5: 1000 | D5: =IF('INCOME '!C4>C5," ഇനിയും "&('INCOME '!C4-C5)&" രൂപ ഉണ്ട്",IF(C5>'INCOME '!C4,(C5-'INCOME '!C4)&" രൂപ അധിക ചിലവ് . ","തുക tally ആയി")) -> ഇനിയും 41945 രൂപ ഉണ്ട്
A6: 46144 | B6: 10K Personal Loan | C6: 1000 | D6: =IF('INCOME '!C4>C6-C5," ഇനിയും "&('INCOME '!C4-C6-C5)&" രൂപ ഉണ്ട്",IF(C6-C5>'INCOME '!C4,(C6-C5-'INCOME '!C4)&" രൂപ അധിക ചിലവ് . ","തുക tally ആയി")) -> ഇനിയും 40945 രൂപ ഉണ്ട്
A7: 46144 | B7: 50K Personal Loan | C7: 2251 | D7: =IF('INCOME '!C4>C7-C6-C5," ഇനിയും "&('INCOME '!C4-C7-C6-C5)&" രൂപ ഉണ്ട്",IF(C7-C6-C5>'INCOME '!C4,(C7-C6-C5-'INCOME '!C5)&" രൂപ അധിക ചിലവ് . ","തുക tally ആയി")) -> ഇനിയും 38694 രൂപ ഉണ്ട്
A8: 46144 | B8: JBL Speaker EMI | C8: 1886 | D8: =IF('INCOME '!C4>C8-C7-C6-C5," ഇനിയും "&('INCOME '!C4-C8-C7-C6-C5)&" രൂപ ഉണ്ട്",IF(C8-C7-C6-C5>'INCOME '!C4,(C8-C7-C6-C5-'INCOME '!C4)&" രൂപ അധിക ചിലവ് . ","തുക tally ആയി")) -> ഇനിയും 36808 രൂപ ഉണ്ട്
A9: 46147 | B9: 30K Personal Loan | C9: 1643 | D9: =IF('INCOME '!C4>C9-C8-C7-C6-C5," ഇനിയും "&('INCOME '!C4-C9-C8-C7-C6-C5)&" രൂപ ഉണ്ട്",IF(C9-C8-C7-C6-C5>'INCOME '!C4,(C9-C8-C7-C6-C5-'INCOME '!C4)&" രൂപ അധിക ചിലവ് . ","തുക tally ആയി")) -> ഇനിയും 35165 രൂപ ഉണ്ട്
A10: 46147 | B10: Ola Scooter EMI | C10: 3883 | D10: =IF('INCOME '!C4>C9-C8-C7-C6-C5-C10," ഇനിയും "&('INCOME '!C4-C9-C8-C7-C6-C5-C10)&" രൂപ ഉണ്ട്",IF(C9-C8-C7-C6-C5>'INCOME '!C4,(C9-C8-C7-C6-C5-C10-'INCOME '!C4)&" രൂപ അധിക ചിലവ് . ","തുക tally ആയി")) -> ഇനിയും 31282 രൂപ ഉണ്ട്
A11: 46147 | B11: Activa Scooter EMI | C11: 2699 | D11: =IF('INCOME '!C4>C9-C8-C7-C6-C5-C10-C11," ഇനിയും "&('INCOME '!C4-C9-C8-C7-C6-C5-C11-C10)&" രൂപ ഉണ്ട്",IF(C9-C8-C11-C7-C6-C5>'INCOME '!C4,(C9-C8-C7-C6-C5-C10-C11-'INCOME '!C4)&" രൂപ അധിക ചിലവ് . ","തുക tally ആയി")) -> ഇനിയും 28583 രൂപ ഉണ്ട്
A12: 46147 | B12: Ayal Koottam Loan | C12: 2500 | D12: =IF('INCOME '!C4>C9-C8-C7-C6-C5-C10-C11-C12," ഇനിയും "&('INCOME '!C4-C9-C8-C7-C6-C12-C5-C11-C10)&" രൂപ ഉണ്ട്",IF(C9-C8-C11-C7-C6-C5-C12>'INCOME '!C4,(C9-C8-C7-C6-C5-C10-C11-C12-'INCOME '!C4)&" രൂപ അധിക ചിലവ് . ","തുക tally ആയി")) -> ഇനിയും 26083 രൂപ ഉണ്ട്
A13: 46149 | B13: House Rent | C13: 5000 | D13: =IF('INCOME '!C4>C9-C8-C7-C6-C5-C10-C11-C12-C13," ഇനിയും "&('INCOME '!C4-C9-C8-C7-C6-C12-C5-C11-C10-C13)&" രൂപ ഉണ്ട്",IF(C9-C8-C11-C7-C6-C5-C12-C13>'INCOME '!C4,(C9-C8-C7-C6-C5-C10-C11-C12-C13-'INCOME '!C4)&" രൂപ അധിക ചിലവ് . ","തുക tally ആയി")) -> ഇനിയും 21083 രൂപ ഉണ്ട്
A14: 46153 | B14: Car Loan | C14: 11300 | D14: =IF('INCOME '!C4>C9-C8-C7-C6-C5-C10-C11-C12-C13-C14," ഇനിയും "&('INCOME '!C4-C9-C8-C7-C6-C12-C5-C11-C10-C13-C14)&" രൂപ ഉണ്ട്",IF(C9-C8-C11-C7-C6-C5-C12-C13-C14>'INCOME '!C4,(C9-C8-C7-C6-C5-C10-C11-C12-C13-C14-'INCOME '!C4)&" രൂപ അധിക ചിലവ് . ","തുക tally ആയി")) -> ഇനിയും 9783 രൂപ ഉണ്ട്
B15: Mobile Recharge | C15: =400+220+220 -> 840 | D15: =IF('INCOME '!C4>C9-C8-C7-C6-C5-C10-C11-C12-C13-C14-C15," ഇനിയും "&('INCOME '!C4-C9-C8-C7-C6-C12-C5-C11-C10-C13-C14-C15)&" രൂപ ഉണ്ട്",IF(C9-C8-C11-C7-C6-C5-C12-C13-C14-C15>'INCOME '!C4,(C9-C8-C7-C6-C5-C10-C11-C12-C13-C14-C15-'INCOME '!C4)&" രൂപ അധിക ചിലവ് . ","തുക tally ആയി")) -> ഇനിയും 8943 രൂപ ഉണ്ട്
B16: Wifi Recharge | C16: 350 | D16: =IF('INCOME '!C4>C9-C8-C7-C6-C5-C10-C11-C12-C13-C14-C15-C16," ഇനിയും "&('INCOME '!C4-C9-C8-C7-C6-C12-C5-C11-C10-C13-C14-C15-C16)&" രൂപ ഉണ്ട്",IF(C9-C8-C11-C7-C6-C5-C12-C13-C14-C15>'INCOME '!C4,(C9-C8-C7-C6-C5-C10-C11-C12-C13-C14-C15-C16-'INCOME '!C4)&" രൂപ അധിക ചിലവ് . ","തുക tally ആയി")) -> ഇനിയും 8593 രൂപ ഉണ്ട്
B17: Current bill | C17: 1500 | D17: =IF('INCOME '!C4>C9-C8-C7-C6-C5-C10-C11-C12-C13-C14-C15-C16-C17," ഇനിയും "&('INCOME '!C4-C9-C8-C7-C6-C12-C5-C11-C10-C13-C14-C15-C16-C17)&" രൂപ ഉണ്ട്",IF(C9-C8-C11-C7-C6-C5-C12-C13-C14-C15-C16-C17>'INCOME '!C4,(C9-C8-C7-C6-C5-C10-C11-C12-C13-C14-C15-C16-C17-'INCOME '!C4)&" രൂപ അധിക ചിലവ് . ","തുക tally ആയി")) -> ഇനിയും 7093 രൂപ ഉണ്ട്

Sheet ENTERTAINMENT 
A1: ='INCOME '!C4-'LIABILITIES OR EMI'!C4 -> 7093
A2: ='LIABILITIES OR EMI'!B3-B4 -> -6180
A3: Date | B3: Cash Out
B4: =SUM(B5:B35) -> 10773
A5: 46143 | B5: 0
A6: 46144 | B6: =24+36+95+50+24 -> 229
A7: 46145 | B7: =10+100+200+100 -> 410
A8: 46146
A9: 46147 | B9: =325+180+50+100 -> 655
A10: 46148 | B10: =500+100+40+350 -> 990
A11: 46149 | B11: =80+48+110 -> 238
A12: 46150 | B12: =50+60+130+20+50+30+500 -> 840
A13: 46151 | B13: =84+150 -> 234
A14: 46152 | B14: =13+100+150 -> 263
A15: 46153 | B15: =15 -> 15
A16: 46154 | B16: =10+42 -> 52
A17: 46155 | B17: =4+31+26+7 -> 68
A18: 46156 | B18: =10+58 -> 68
A19: 46157 | B19: =15+30+100+60+550+650+1000 -> 2405
A20: 46158 | B20: =627+200+250 -> 1077
A21: 46159 | B21: =500+105+630 -> 1235
A22: 46160 | B22: =200+30+80+500+50+80+100+332 -> 1372
A23: 46161 | B23: =60+36 -> 96
A24: 46162 | B24: =36+200+100+48 -> 384
A25: 46163 | B25: =30+37 -> 67
A26: 46164 | B26: =29 -> 29
A27: 46165
A28: 46166
A29: 46167
A30: 46168 | B30: =26+20 -> 46
A31: 46169
A32: 46170
A33: 46171
A34: 46172
A35: 46173
A36: =IF('LIABILITIES OR EMI'!B3>B4," ഇനിയും "&('LIABILITIES OR EMI'!B3-B4)&" രൂപ ബാക്കിയുണ്ട്",IF(B4>'LIABILITIES OR EMI'!B3,(B4-'LIABILITIES OR EMI'!B3)&" രൂപ അധികം ചിലവായി","പണം തീര്‍ന്നു ")) -> 6180 രൂപ അധികം ചിലവായി

Sheet PETROL
A1: =IF(USUAL!B31>B3," ഇനിയും "&(USUAL!B31-B3)&" രൂപ ബാക്കിയുണ്ട്",IF(B3>USUAL!B31,(B3-USUAL!B31)&" രൂപ അധികം ചിലവായി","പണം തീര്‍ന്നു ")) -> പണം തീര്‍ന്നു
A2: Date | B2: Cash Out
B3: =SUM(B4:B21) -> 1500
A4: 46159 | B4: 1000
A5: 46167 | B5: 500

Sheet UN EXPECTED
A1: =IF(USUAL!B32>C34," ഇനിയും "&(USUAL!B32-C34)&" രൂപ ബാക്കിയുണ്ട്",IF(C34>USUAL!B32,(C34-USUAL!B32)&" രൂപ അധികം ചിലവായി","പണം തീര്‍ന്നു ")) -> 1106 രൂപ അധികം ചിലവായി
A2: Date | B2: Details | C2: Cash Out
A3: 46143
A4: 46144
A5: 46145
A6: 46146 | B6: Screen guard | C6: 280
A7: 46147
A8: 46148
A9: 46149
A10: 46150
A11: 46151
A12: 46152
A13: 46153
A14: 46154
A15: 46155
A16: 46156
A17: 46157
A18: 46158
... A26: 46166
A27: 46167 | B27: ചെടി | C27: 350
A28: 46168 | B28: ANI | C28: 500
A29: 46169
A30: 46170
A31: 46171
A32: 46172
A33: 46173
C34: =SUM(C3:C33) -> 1130

Sheet MONTHLY SUMMARY 
A1: PARTICLAR | B1: CREDIT | C1: EBIT | D1: WARNING
A2: TOTAL INCOME | B2: ='INCOME '!C4 -> 42945 | C2: 0 | D2: =IF(USUAL!B7>B2," ഇനിയും "&(USUAL!B7-B2)&" രൂപ കിട്ടാനുണ്ട്",IF(B2>USUAL!B7,(B2-USUAL!B7)&" രൂപ അധിക ചിലവ് . ","തുക tally ആയി")) -> ഇനിയും 55 രൂപ കിട്ടാനുണ്ട്
A3: EMI & HOUSE RENT | C3: ='LIABILITIES OR EMI'!C4 -> 35852 | D3: =IF(USUAL!B27>C3," ഇനിയും "&(USUAL!B27-C3)&" രൂപയുടെ ബാധ്യതയുണ്ട്",IF(C3>USUAL!B27,(C3-USUAL!B27)&" രൂപ അധിക ചിലവ് . ","തുക tally ആയി")) -> ഇനിയും 4623.57 രൂപയുടെ ബാധ്യതയുണ്ട്
A4: PERSONAL ENTERTAINMENT | C4: ='ENTERTAINMENT '!B4 -> 10773 | D4: =IF('LIABILITIES OR EMI'!B3>C4," ഇനിയും "&('LIABILITIES OR EMI'!B3-C4)&" രൂപ ബാക്കിയുണ്ട്",IF(C4>'LIABILITIES OR EMI'!B3,(C4-'LIABILITIES OR EMI'!B3)&" രൂപ അധികം ചിലവായി","പണം തീര്‍ന്നു ")) -> 6180 രൂപ അധികം ചിലവായി
A5: PETROL EXPENSE | C5: =PETROL!B3 -> 1500 | D5: =IF(USUAL!B31>C5," ഇനിയും "&(USUAL!B31-C5)&" രൂപ ബാക്കിയുണ്ട്",IF(C5>USUAL!B31,(C5-USUAL!B31)&" രൂപ അധികം ചിലവായി","പണം തീര്‍ന്നു ")) -> പണം തീര്‍ന്നു
A6: OTHER EXPENSE | C6: ='UN EXPECTED'!C34 -> 1130 | D6: =IF(USUAL!B32>C6," ഇനിയും "&(USUAL!B32-C6)&" രൂപ ബാക്കിയുണ്ട്",IF(C6>USUAL!B32,(C6-USUAL!B32)&" രൂപ അധികം ചിലവായി","പണം തീര്‍ന്നു ")) -> 1106 രൂപ അധികം ചിലവായി
B7: =SUM(B2:B6) -> 42945 | C7: =SUM(C2:C6) -> 49255
A8: SAVINGS | C8: =B2-(C3+C4+C5+C6) -> -6310 | D8: =IF(B2>C3," ഇനിയും "&(B2-C3)&" രൂപ ബാക്കിയുണ്ട്",IF('INCOME '!C4>+C6,(B2-C3+C4+C5+C6)&" രൂപ അധികം ചിലവായി","പണം തീര്‍ന്നു ")) -> ഇനിയും 7093 രൂപ ബാക്കിയുണ്ട്
